vktools/.git/config
vktools/.git/description
vktools/.git/HEAD
vktools/.git/hooks/applypatch-msg.sample
vktools/.git/hooks/commit-msg.sample
vktools/.git/hooks/fsmonitor-watchman.sample
vktools/.git/hooks/post-update.sample
vktools/.git/hooks/pre-applypatch.sample
vktools/.git/hooks/pre-commit.sample
vktools/.git/hooks/pre-merge-commit.sample
vktools/.git/hooks/pre-push.sample
vktools/.git/hooks/pre-rebase.sample
vktools/.git/hooks/pre-receive.sample
vktools/.git/hooks/prepare-commit-msg.sample
vktools/.git/hooks/update.sample
vktools/.git/index
vktools/.git/info/exclude
vktools/.git/logs/HEAD
vktools/.git/logs/refs/heads/main
vktools/.git/logs/refs/remotes/origin/HEAD
vktools/.git/objects/pack/pack-8f74fd839e48e064ac411939029f4e092faf693c.idx
vktools/.git/objects/pack/pack-8f74fd839e48e064ac411939029f4e092faf693c.pack
vktools/.git/packed-refs
vktools/.git/refs/heads/main
vktools/.git/refs/remotes/origin/HEAD
vktools/__init__.py
vktools/vk_api_tools.py
vktools-1.0.3.dist-info/WHEEL
vktools-1.0.3.dist-info/METADATA
vktools-1.0.3.dist-info/RECORD
