Metadata-Version: 2.1
Name: vktools
Version: 1.0.3
Summary: https://github.com/Fsoky/vktools
Author: Fsoky
Author-email: cyberuest0x12@gmail.com
Requires-Python: >=3.8,<4.0
Classifier: Programming Language :: Python :: 3
Classifier: Programming Language :: Python :: 3.8
